vpklr/__init__.py
vpklr/vpklr.py
vpklr-0.1.dist-info/METADATA
vpklr-0.1.dist-info/WHEEL
vpklr-0.1.dist-info/top_level.txt
vpklr-0.1.dist-info/RECORD
